tokenizer_spln/__init__.py
tokenizer_spln-0.5.dist-info/entry_points.txt
tokenizer_spln-0.5.dist-info/WHEEL
tokenizer_spln-0.5.dist-info/METADATA
tokenizer_spln-0.5.dist-info/RECORD
