Metadata-Version: 2.1
Name: tokenizer_spln
Version: 0.5
Summary: Módulo para tokanizar livros
Author-email: Tiago Silva <tiagoluisdiassilva@gmail.com>
Project-URL: Home, https://github.com/surumkata/spln-2223/tree/main/TPC4
